github_project_mcp/__init__.py
github_project_mcp/cli.py
github_project_mcp/server.py
github_project_mcp-0.1.1.dist-info/licenses/LICENSE
github_project_mcp-0.1.1.dist-info/METADATA
github_project_mcp-0.1.1.dist-info/WHEEL
github_project_mcp-0.1.1.dist-info/entry_points.txt
github_project_mcp-0.1.1.dist-info/top_level.txt
github_project_mcp-0.1.1.dist-info/RECORD
