Metadata-Version: 2.4
Name: github-project-mcp
Version: 0.1.1
Summary: A Model Context Protocol server for managing GitHub projects and issues via GraphQL
Home-page: https://github.com/jaqarx/github-project-mcp
Author: Enrica Tan
Author-email: Enrica Tan <tanenrica@gmail.com>
License: MIT
Project-URL: Homepage, https://github.com/yourusername/github-project-mcp
Project-URL: Documentation, https://github.com/yourusername/github-project-mcp#readme
Project-URL: Repository, https://github.com/yourusername/github-project-mcp
Project-URL: Issues, https://github.com/yourusername/github-project-mcp/issues
Keywords: github,mcp,graphql,api,project-management
Classifier: Development Status :: 3 - Alpha
Classifier: Intended Audience :: Developers
Classifier: Topic :: Software Development :: Libraries :: Python Modules
Classifier: License :: OSI Approved :: MIT License
Classifier: Programming Language :: Python :: 3.10
Classifier: Programming Language :: Python :: 3.11
Classifier: Programming Language :: Python :: 3.12
Requires-Python: >=3.10
License-File: LICENSE
Requires-Dist: mcp>=0.9.0
Requires-Dist: httpx>=0.27.0
Requires-Dist: python-dotenv>=1.0.0
Requires-Dist: click>=8.1.0
Requires-Dist: rich>=13.0.0
Dynamic: author
Dynamic: home-page
Dynamic: license-file
Dynamic: requires-python
